plink/__init__.py
plink/__main__.py
plink/analyser.py
plink/consts.py
plink/options.py
plink/result.py
plink_url-1.1.0.dist-info/LICENSE
plink_url-1.1.0.dist-info/METADATA
plink_url-1.1.0.dist-info/WHEEL
plink_url-1.1.0.dist-info/entry_points.txt
plink_url-1.1.0.dist-info/top_level.txt
plink_url-1.1.0.dist-info/RECORD
