Metadata-Version: 2.1
Name: plink-url
Version: 1.1.0
Summary: Recursively analyse a URL and it's children
Author-email: Jessica Ward <jessicawardiom@gmail.com>
License: MIT License
Project-URL: Homepage, https://github.com/Jessicaward/plink
Keywords: cli,url,link,analysis,network,test
Classifier: License :: OSI Approved :: MIT License
Classifier: Programming Language :: Python
Classifier: Programming Language :: Python :: 3
Requires-Python: >=3.7
License-File: LICENSE
Requires-Dist: beautifulsoup4 (>=4.11.2)
Requires-Dist: requests (>=2.28.2)
Requires-Dist: termcolor (>=2.2.0)
